{
  "code": 200,
  "status": "OK",
  "data": {
    "Item": {
      "Id": "6a45214d-5fef-4c46-b51a-12b9528b0d49",
      "Contents": [
        {
          "Id": "da7233bc-a838-44ac-9f03-63ab0712497d",
          "Url": "https://raw.githubusercontent.com/Bedrock-Cosmos/Backend/refs/heads/main/Main/Packs/Persona/Zeqa/Black Butterfly.zip",
          "MaxClientVersion": "65535.65535.65535",
          "MinClientVersion": "1.16.0",
          "Type": "personabinary"
        }
      ],
      "DisplayProperties": {
        "creatorName": "Zeqa",
        "originalCreatorId": "50dead25-46c1-4dd4-8f63-f8403716fcb9",
        "purchasable": true,
        "packIdentity": [
          {
            "type": "persona_piece",
            "uuid": "28589e4c-b2d1-497f-8be7-2ea558002d23",
            "version": "1.0.0"
          }
        ]
      }
    }
  }
}