{
  "code": 200,
  "status": "OK",
  "data": {
    "Item": {
      "Id": "c30bdb6a-9108-42fa-b9c5-4012c7a7f7a3",
      "Contents": [
        {
          "Id": "bf62704a-d044-456a-8456-81a91f102a94",
          "Url": "https://raw.githubusercontent.com/Bedrock-Cosmos/Backend/refs/heads/main/Main/Packs/Persona/Zeqa/Moon.zip",
          "MaxClientVersion": "65535.65535.65535",
          "MinClientVersion": "1.16.0",
          "Type": "personabinary"
        }
      ],
      "DisplayProperties": {
        "creatorName": "Zeqa",
        "originalCreatorId": "50dead25-46c1-4dd4-8f63-f8403716fcb9",
        "purchasable": true,
        "packIdentity": [
          {
            "type": "persona_piece",
            "uuid": "b5d9bfe2-75f4-46ac-9171-c9abf19623e3",
            "version": "1.0.0"
          }
        ]
      }
    }
  }
}