{
  "code": 200,
  "status": "OK",
  "data": {
    "Item": {
      "Id": "7e6b3ab5-80d9-44e6-bd40-21fac91131d4",
      "Contents": [
        {
          "Id": "47e9c833-f9af-4514-a72a-b4b38a80b9eb",
          "Url": "https://raw.githubusercontent.com/Bedrock-Cosmos/Backend/refs/heads/main/Main/Packs/Persona/Zeqa/Pastel MLG.zip",
          "MaxClientVersion": "65535.65535.65535",
          "MinClientVersion": "1.16.0",
          "Type": "personabinary"
        }
      ],
      "DisplayProperties": {
        "creatorName": "Zeqa",
        "originalCreatorId": "50dead25-46c1-4dd4-8f63-f8403716fcb9",
        "purchasable": true,
        "packIdentity": [
          {
            "type": "persona_piece",
            "uuid": "3b304f8d-356d-4aaa-9363-b78b4e36cc51",
            "version": "1.0.0"
          }
        ]
      }
    }
  }
}