{
  "code": 200,
  "status": "OK",
  "data": {
    "Item": {
      "Id": "c5642772-d9ab-4963-9719-c54be94feba2",
      "Contents": [
        {
          "Id": "e0e1a8a1-53a9-4200-8482-fa9b7f470546",
          "Url": "https://raw.githubusercontent.com/Bedrock-Cosmos/Backend/refs/heads/main/Main/Packs/Persona/Zeqa/Sunset_1.zip",
          "MaxClientVersion": "65535.65535.65535",
          "MinClientVersion": "1.16.0",
          "Type": "personabinary"
        }
      ],
      "DisplayProperties": {
        "creatorName": "Zeqa",
        "originalCreatorId": "50dead25-46c1-4dd4-8f63-f8403716fcb9",
        "purchasable": true,
        "packIdentity": [
          {
            "type": "persona_piece",
            "uuid": "4b2b3cc0-ad4b-43a3-adc2-f1311d34d7f3",
            "version": "1.0.0"
          }
        ]
      }
    }
  }
}