{
  "code": 200,
  "status": "OK",
  "data": {
    "Item": {
      "Id": "8d746d35-8d2d-47da-aa91-1170afc90156",
      "Contents": [
        {
          "Id": "53b5834b-1dfa-4275-9b4c-57377deb819c",
          "Url": "https://raw.githubusercontent.com/Bedrock-Cosmos/Backend/refs/heads/main/Main/Packs/Persona/Zeqa/Valentine 2022 - White Heart.zip",
          "MaxClientVersion": "65535.65535.65535",
          "MinClientVersion": "1.16.0",
          "Type": "personabinary"
        }
      ],
      "DisplayProperties": {
        "creatorName": "Zeqa",
        "originalCreatorId": "50dead25-46c1-4dd4-8f63-f8403716fcb9",
        "purchasable": true,
        "packIdentity": [
          {
            "type": "persona_piece",
            "uuid": "15707f46-4b41-4ade-bab0-69ffa22a5867",
            "version": "1.0.0"
          }
        ]
      }
    }
  }
}